aws_get_vpn_connection_info/__init__.py
aws_get_vpn_connection_info/tasks.py
aws_get_vpn_connection_info-0.43.dist-info/DESCRIPTION.rst
aws_get_vpn_connection_info-0.43.dist-info/METADATA
aws_get_vpn_connection_info-0.43.dist-info/RECORD
aws_get_vpn_connection_info-0.43.dist-info/WHEEL
aws_get_vpn_connection_info-0.43.dist-info/metadata.json
aws_get_vpn_connection_info-0.43.dist-info/top_level.txt
